s3x/__init__.py
s3x/count.py
s3x/main.py
s3x/size.py
s3x/utils/__init__.py
s3x/utils/aws.py
s3x-0.1.0.dist-info/entry_points.txt
s3x-0.1.0.dist-info/WHEEL
s3x-0.1.0.dist-info/METADATA
s3x-0.1.0.dist-info/RECORD
