Metadata-Version: 2.1
Name: s3x
Version: 0.1.0
Summary: 
Author: Dan Sikes
Author-email: dansikes7@gmail.com
Requires-Python: >=3.9,<4.0
Classifier: Programming Language :: Python :: 3
Classifier: Programming Language :: Python :: 3.9
Requires-Dist: tqdm (>=4.62.3,<5.0.0)
